error_detect/__init__.py
error_detect/core.py
error_detect-0.1.0.dist-info/METADATA
error_detect-0.1.0.dist-info/WHEEL
error_detect-0.1.0.dist-info/top_level.txt
error_detect-0.1.0.dist-info/RECORD
