Metadata-Version: 2.1
Name: error_detect
Version: 0.1.0
Summary: A package for detecting errors and generating solutions using an LLM API.
Home-page: https://github.com/Rhul27/error_detect
Author: Rahul Gond
Author-email: 27rg2000@gmail.com
Classifier: Programming Language :: Python :: 3
Classifier: License :: OSI Approved :: MIT License
Classifier: Operating System :: OS Independent
Requires-Python: >=3.6
Requires-Dist: requests
